sphinx_jinja/__init__.py
sphinx_jinja-2.0.2.dist-info/LICENSE
sphinx_jinja-2.0.2.dist-info/WHEEL
sphinx_jinja-2.0.2.dist-info/METADATA
sphinx_jinja-2.0.2.dist-info/RECORD
