Metadata-Version: 2.1
Name: sphinx-jinja
Version: 2.0.2
Summary: includes jinja templates in a documentation
Home-page: https://github.com/tardyp/sphinx-jinja
License: MIT
Keywords: sphinx,jinja
Author: Pierre Tardy
Author-email: tardyp@gmail.com
Requires-Python: >=3.6,<4
Classifier: License :: OSI Approved :: MIT License
Classifier: Programming Language :: Python :: 3
Classifier: Programming Language :: Python :: 3.10
Classifier: Programming Language :: Python :: 3.6
Classifier: Programming Language :: Python :: 3.7
Classifier: Programming Language :: Python :: 3.8
Classifier: Programming Language :: Python :: 3.9
Requires-Dist: Jinja2 (>=2.11)
Requires-Dist: docutils (>=0.16)
Requires-Dist: sphinx (>4.2.0)
Project-URL: Repository, https://github.com/tardyp/sphinx-jinja
